prettyTables/__init__.py
prettyTables/cells.py
prettyTables/columns.py
prettyTables/options.py
prettyTables/style_compositions.py
prettyTables/table.py
prettyTables/table_strings.py
prettyTables/test.py
prettyTables/utils.py
prettyTables-1.1.4.dist-info/LICENSE
prettyTables-1.1.4.dist-info/LICENSE.txt
prettyTables-1.1.4.dist-info/METADATA
prettyTables-1.1.4.dist-info/WHEEL
prettyTables-1.1.4.dist-info/top_level.txt
prettyTables-1.1.4.dist-info/RECORD
