Metadata-Version: 2.1
Name: prettyTables
Version: 1.1.4
Summary: Tables to print in console
Home-page: https://github.com/Kyostenas/prettyTables
Download-URL: 
Author: Benjamin Ramirez
Author-email: chilerito12@gmail.com
License: MIT
Keywords: console,graphics
Classifier: Development Status :: 4 - Beta
Classifier: Intended Audience :: Developers
Classifier: Topic :: Software Development :: Build Tools
Classifier: License :: OSI Approved :: MIT License
Classifier: Programming Language :: Python :: 3.8
Classifier: Programming Language :: Python :: 3.9
License-File: LICENSE
License-File: LICENSE.txt
